google_apis/__init__.py
google_apis/bid_manager.py
google_apis/display_video.py
google_apis/gmail.py
google_apis/google_api.py
google_apis/gsheet.py
google_apis/manufacturer_center.py
google_apis/search_ads.py
google_apis_python_cloudcity-0.0.2.dist-info/METADATA
google_apis_python_cloudcity-0.0.2.dist-info/WHEEL
google_apis_python_cloudcity-0.0.2.dist-info/top_level.txt
google_apis_python_cloudcity-0.0.2.dist-info/RECORD
