Metadata-Version: 2.1
Name: google-apis-python-cloudcity
Version: 0.0.2
Summary: UNKNOWN
Home-page: UNKNOWN
License: UNKNOWN
Platform: UNKNOWN
Requires-Dist: google-api-python-client
Requires-Dist: wget
Requires-Dist: google-auth-oauthlib
